ecoact_ml_company/__init__.py
ecoact_ml_company/db_model/__init__.py
ecoact_ml_company/domain_model/__init__.py
ecoact_ml_company-0.0.1.dist-info/METADATA
ecoact_ml_company-0.0.1.dist-info/WHEEL
ecoact_ml_company-0.0.1.dist-info/RECORD
